.gitignore
AUTHORS.txt
CHANGES.txt
LICENSE.txt
MANIFEST.in
README.md
pyproject.toml
docs/Makefile
docs/conf.py
docs/index.rst
docs/make.bat
pytweening/__init__.py
pytweening.egg-info/PKG-INFO
pytweening.egg-info/SOURCES.txt
pytweening.egg-info/dependency_links.txt
pytweening.egg-info/top_level.txt
tests/basicTests.py
tests/generateExcelGraphs.py
tests/graphs.ipynb
tests/graphs.xlsx
tests/seeGraphs.py